{"name":"(Spanish) Verify states in the Spanish declared disaster map are clickable","id":"stories/fullRegression/regressionChecklistSpanish.story;(Spanish) Verify states in the Spanish declared disaster map are clickable","testSteps":[{"number":1,"description":"Given I am on the Spanish Disaster Assistance homepage","duration":4,"startTime":"2018-01-30T14:29:50.026-05:00[America/New_York]","result":"IGNORED","precondition":false,"children":[{"number":2,"description":"Open page: /es","duration":0,"startTime":"2018-01-30T14:29:50.030-05:00[America/New_York]","result":"IGNORED","precondition":false}]},{"number":3,"description":"When I am viewing the declared disaster map","duration":10113,"startTime":"2018-01-30T14:29:50.031-05:00[America/New_York]","result":"IGNORED","precondition":false,"children":[{"number":4,"description":"Check disaster map","duration":10111,"startTime":"2018-01-30T14:29:50.032-05:00[America/New_York]","result":"IGNORED","precondition":false}]},{"number":5,"description":"Then states with disasters should be clickable","duration":2,"startTime":"2018-01-30T14:30:00.144-05:00[America/New_York]","result":"IGNORED","precondition":false,"children":[{"number":6,"description":"Check states","duration":1,"startTime":"2018-01-30T14:30:00.145-05:00[America/New_York]","result":"IGNORED","precondition":false}]}],"userStory":{"id":"regressionChecklistSpanish","storyName":"Regression checklist spanish","path":"stories/fullRegression/regressionChecklistSpanish.story","narrative":"In order to assert that the basic functionality of https://www.disasterassistance.gov/es/ is working\nAs a tester\nI want to run the daily regressions at least twice a day\n\nMeta: @skip","type":"story"},"featureTag":{"name":"Full regression/Regression checklist spanish","type":"story"},"title":"(Spanish) Verify states in the Spanish declared disaster map are clickable","tags":[{"name":"Full regression/Regression checklist spanish","type":"story"},{"name":"Full regression","type":"feature"}],"startTime":"2018-01-30T14:29:50.024-05:00[America/New_York]","duration":0,"projectKey":"","annotatedResult":"SKIPPED","manual":false,"testSource":"JBehave","result":"SKIPPED"}