{"name":"(Spanish) Verify Spanish benefits results display according to use cases","id":"stories/fullRegression/regressionChecklistSpanish.story;(Spanish) Verify Spanish benefits results display according to use cases","testSteps":[{"number":1,"description":"Given I am on the Find Assistance Spanish page","duration":7,"startTime":"2018-01-30T14:31:31.237-05:00[America/New_York]","result":"IGNORED","precondition":false,"children":[{"number":2,"description":"Open page: /es/obtener-asistencia/encontrar-ayuda","duration":0,"startTime":"2018-01-30T14:31:31.243-05:00[America/New_York]","result":"IGNORED","precondition":false}]},{"number":3,"description":"When I choose only Employment","duration":10109,"startTime":"2018-01-30T14:31:31.244-05:00[America/New_York]","result":"IGNORED","precondition":false,"children":[{"number":4,"description":"Get employment results","duration":10107,"startTime":"2018-01-30T14:31:31.245-05:00[America/New_York]","result":"IGNORED","precondition":false}]},{"number":5,"description":"Then I should obtain 9 results and see all the content under the accordions","duration":3008,"startTime":"2018-01-30T14:31:41.353-05:00[America/New_York]","result":"IGNORED","precondition":false,"children":[{"number":6,"description":"Verify employment results and visibility","duration":3006,"startTime":"2018-01-30T14:31:41.355-05:00[America/New_York]","result":"IGNORED","precondition":false}]}],"userStory":{"id":"regressionChecklistSpanish","storyName":"Regression checklist spanish","path":"stories/fullRegression/regressionChecklistSpanish.story","narrative":"In order to assert that the basic functionality of https://www.disasterassistance.gov/es/ is working\nAs a tester\nI want to run the daily regressions at least twice a day\n\nMeta: @skip","type":"story"},"featureTag":{"name":"Full regression/Regression checklist spanish","type":"story"},"title":"(Spanish) Verify Spanish benefits results display according to use cases","tags":[{"name":"Full regression/Regression checklist spanish","type":"story"},{"name":"Full regression","type":"feature"}],"startTime":"2018-01-30T14:31:31.236-05:00[America/New_York]","duration":0,"projectKey":"","annotatedResult":"SKIPPED","manual":false,"testSource":"JBehave","result":"SKIPPED"}